[
  {
    "id": 1770815406954,
    "name": "ytyt.xlsx",
    "uploadedAt": "2026-02-25 17:41:28",
    "lastActivatedAt": null,
    "deletedAt": "2026-02-26 11:55:51",
    "deletedBy": "oleg",
    "totalRows": 5572,
    "availableRows": 4500
  },
  {
    "id": 1770815923135,
    "name": "проба.xlsx",
    "uploadedAt": "2026-02-25 17:41:28",
    "lastActivatedAt": null,
    "deletedAt": "2026-02-26 11:55:54",
    "deletedBy": "oleg",
    "totalRows": 1062,
    "availableRows": 0
  },
  {
    "id": 1770815413350,
    "name": "1к израиль пидоры.xlsx",
    "uploadedAt": "2026-02-25 17:41:28",
    "lastActivatedAt": "2026-02-26 08:36:16",
    "deletedAt": "2026-02-26 11:55:57",
    "deletedBy": "oleg",
    "totalRows": 1500,
    "availableRows": 150
  },
  {
    "id": 1771158329440,
    "name": "999.xlsx",
    "uploadedAt": "2026-02-25 17:41:28",
    "lastActivatedAt": null,
    "deletedAt": "2026-02-26 11:56:04",
    "deletedBy": "oleg",
    "totalRows": 852,
    "availableRows": 0
  },
  {
    "id": 1771243373209,
    "name": "996.xlsx",
    "uploadedAt": "2026-02-25 17:41:28",
    "lastActivatedAt": null,
    "deletedAt": "2026-02-26 11:56:10",
    "deletedBy": "oleg",
    "totalRows": 1500,
    "availableRows": 0
  },
  {
    "id": 1771325115279,
    "name": "conts111.xlsx",
    "uploadedAt": "2026-02-25 17:41:28",
    "lastActivatedAt": null,
    "deletedAt": "2026-02-26 11:56:18",
    "deletedBy": "oleg",
    "totalRows": 287,
    "availableRows": 0
  },
  {
    "id": 1770899409990,
    "name": "1233.xlsx",
    "uploadedAt": "2026-02-25 17:41:28",
    "lastActivatedAt": null,
    "deletedAt": "2026-02-26 11:56:21",
    "deletedBy": "oleg",
    "totalRows": 9,
    "availableRows": 0
  },
  {
    "id": 1771169637791,
    "name": "998.xlsx",
    "uploadedAt": "2026-02-25 17:41:28",
    "lastActivatedAt": null,
    "deletedAt": "2026-02-26 11:56:21",
    "deletedBy": "oleg",
    "totalRows": 1000,
    "availableRows": 0
  },
  {
    "id": 1771401979315,
    "name": "1001.xlsx",
    "uploadedAt": "2026-02-25 17:41:28",
    "lastActivatedAt": null,
    "deletedAt": "2026-02-26 11:56:31",
    "deletedBy": "oleg",
    "totalRows": 12719,
    "availableRows": 0
  },
  {
    "id": 1771234009103,
    "name": "600 номеров.xlsx",
    "uploadedAt": "2026-02-25 17:41:28",
    "lastActivatedAt": null,
    "deletedAt": "2026-02-26 11:56:43",
    "deletedBy": "oleg",
    "totalRows": 603,
    "availableRows": 345
  },
  {
    "id": 1771234006623,
    "name": "600 номеров.xlsx",
    "uploadedAt": "2026-02-25 17:41:28",
    "lastActivatedAt": null,
    "deletedAt": "2026-02-26 11:56:47",
    "deletedBy": "oleg",
    "totalRows": 603,
    "availableRows": 345
  },
  {
    "id": 1771942121517,
    "name": "1001 ndz.xlsx",
    "uploadedAt": "2026-02-25 17:41:28",
    "lastActivatedAt": null,
    "deletedAt": "2026-02-26 11:57:09",
    "deletedBy": "oleg",
    "totalRows": 7340,
    "availableRows": 364
  },
  {
    "id": 1771235930082,
    "name": "997.xlsx",
    "uploadedAt": "2026-02-25 17:41:28",
    "lastActivatedAt": null,
    "deletedAt": "2026-02-26 11:57:13",
    "deletedBy": "oleg",
    "totalRows": 1005,
    "availableRows": 589
  },
  {
    "id": 1770906891254,
    "name": "1700.xlsx",
    "uploadedAt": "2026-02-25 17:41:28",
    "lastActivatedAt": null,
    "deletedAt": "2026-02-26 11:57:16",
    "deletedBy": "oleg",
    "totalRows": 1700,
    "availableRows": 452
  },
  {
    "id": 1772022892809,
    "name": "900.xlsx",
    "uploadedAt": "2026-02-25 17:41:28",
    "lastActivatedAt": "2026-02-25 17:41:58",
    "deletedAt": "2026-02-26 12:13:16",
    "deletedBy": "oleg",
    "totalRows": 2000,
    "availableRows": 59
  },
  {
    "id": 1772089888712,
    "name": "901.xlsx",
    "uploadedAt": "2026-02-26 09:11:28",
    "lastActivatedAt": "2026-02-26 11:55:32",
    "deletedAt": "2026-02-26 14:39:35",
    "deletedBy": "oleg",
    "totalRows": 1000,
    "availableRows": 549
  },
  {
    "id": 1771332551475,
    "name": "995.xlsx",
    "uploadedAt": "2026-02-25 17:41:28",
    "lastActivatedAt": "2026-02-26 13:59:56",
    "deletedAt": "2026-03-01 10:30:15",
    "deletedBy": "oleg",
    "totalRows": 700,
    "availableRows": 0
  },
  {
    "id": 1771334901998,
    "name": "994.xlsx",
    "uploadedAt": "2026-02-25 17:41:28",
    "lastActivatedAt": "2026-02-26 15:29:13",
    "deletedAt": "2026-03-01 10:30:18",
    "deletedBy": "oleg",
    "totalRows": 1496,
    "availableRows": 1
  },
  {
    "id": 1771940476162,
    "name": "1001-2.xlsx",
    "uploadedAt": "2026-02-25 17:41:28",
    "lastActivatedAt": "2026-02-26 14:55:52",
    "deletedAt": "2026-03-01 10:30:29",
    "deletedBy": "oleg",
    "totalRows": 388,
    "availableRows": 0
  },
  {
    "id": 1772348356521,
    "name": "213213123.xlsx",
    "uploadedAt": "2026-03-01 08:59:16",
    "lastActivatedAt": "2026-03-01 08:59:20",
    "deletedAt": "2026-03-01 10:30:34",
    "deletedBy": "oleg",
    "totalRows": 1000,
    "availableRows": 0
  },
  {
    "id": 1772102019572,
    "name": "966.xlsx",
    "uploadedAt": "2026-02-26 12:33:39",
    "lastActivatedAt": "2026-03-01 10:20:12",
    "deletedAt": "2026-03-01 10:30:36",
    "deletedBy": "oleg",
    "totalRows": 993,
    "availableRows": 0
  }
]